Repeteco/__init__.py
Repeteco/leitura_arquivo.py
Repeteco/palavras_repetidas.py
Repeteco-0.0.1.dist-info/METADATA
Repeteco-0.0.1.dist-info/WHEEL
Repeteco-0.0.1.dist-info/top_level.txt
Repeteco-0.0.1.dist-info/RECORD
