Metadata-Version: 2.1
Name: Repeteco
Version: 0.0.1
Summary: Pacote tem como objetivo identificar as palavras mais repetidas em um texto.
Home-page: https://github.com/almeidadeoliveirabruno/Repeteco
Author: Bruno
Author-email: brunoa52@hotmail.com
Requires-Python: >=3.12.4
Requires-Dist: python-docx
